golident/__init__.py
golident-0.1.3.dist-info/METADATA
golident-0.1.3.dist-info/WHEEL
golident-0.1.3.dist-info/licenses/LICENSE-APACHE
golident-0.1.3.dist-info/licenses/LICENSE-MIT
golident-0.1.3.dist-info/RECORD
